Workbook

Sheet Revenue Lead Sheet
A1: Evergreen Inc.
A2: Revenue Lead Sheet
A3: For the Year Ended December 31, 2024
A5: Colour Legend: | B5: ■ Blue = hardcoded input | D5: ■ Black = formula | F5: ■ Green = cross-sheet link
A7: GL Account # | B7: Account Name | C7: Revenue Stream (FS Caption) | D7: Current Year 2024 ($) | E7: Prior Year 2023 ($) | F7: $ Change (CY vs PY) | G7: % Change (CY vs PY)
A8: 800001 | B8: =VLOOKUP(A8,'Year-End TB'!$A:$F,2,0) -> Domestic Direct to Consumer Sales | C8: Domestic DTC Revenue | D8: =VLOOKUP(A8,'Year-End TB'!$A:$F,5,0)*-1 -> 23043496 | E8: =VLOOKUP(A8,'Prior Year TB'!$A:$F,5,0)*-1 -> 20580000 | F8: =D8-E8 -> 2463496 | G8: =IF(E8=0,"-",F8/ABS(E8)) -> 0.1197034
A9: 800002 | B9: =VLOOKUP(A9,'Year-End TB'!$A:$F,2,0) -> AZ Franchise Sales | C9: Domestic Franchise Revenue | D9: =VLOOKUP(A9,'Year-End TB'!$A:$F,5,0)*-1 -> 2229331 | E9: =VLOOKUP(A9,'Prior Year TB'!$A:$F,5,0)*-1 -> 2050000 | F9: =D9-E9 -> 179331 | G9: =IF(E9=0,"-",F9/ABS(E9)) -> 0.087478537
A10: 800003 | B10: =VLOOKUP(A10,'Year-End TB'!$A:$F,2,0) -> CA Franchise Sales | C10: Domestic Franchise Revenue | D10: =VLOOKUP(A10,'Year-End TB'!$A:$F,5,0)*-1 -> 5573328 | E10: =VLOOKUP(A10,'Prior Year TB'!$A:$F,5,0)*-1 -> 5105000 | F10: =D10-E10 -> 468328 | G10: =IF(E10=0,"-",F10/ABS(E10)) -> 0.091739079
A11: 800004 | B11: =VLOOKUP(A11,'Year-End TB'!$A:$F,2,0) -> NYC Franchise Sales | C11: Domestic Franchise Revenue | D11: =VLOOKUP(A11,'Year-End TB'!$A:$F,5,0)*-1 -> 2340798 | E11: =VLOOKUP(A11,'Prior Year TB'!$A:$F,5,0)*-1 -> 2048000 | F11: =D11-E11 -> 292798 | G11: =IF(E11=0,"-",F11/ABS(E11)) -> 0.14296777
A12: 800005 | B12: =VLOOKUP(A12,'Year-End TB'!$A:$F,2,0) -> International Direct to Consumer Sales | C12: International DTC Revenue | D12: =VLOOKUP(A12,'Year-End TB'!$A:$F,5,0)*-1 -> 1003199 | E12: =VLOOKUP(A12,'Prior Year TB'!$A:$F,5,0)*-1 -> 852000 | F12: =D12-E12 -> 151199 | G12: =IF(E12=0,"-",F12/ABS(E12)) -> 0.17746362
A13: 800006 | B13: =VLOOKUP(A13,'Year-End TB'!$A:$F,2,0) -> AUS Franchise Sales | C13: International Franchise Revenue | D13: =VLOOKUP(A13,'Year-End TB'!$A:$F,5,0)*-1 -> 2503381 | E13: =VLOOKUP(A13,'Prior Year TB'!$A:$F,5,0)*-1 -> 2205000 | F13: =D13-E13 -> 298381 | G13: =IF(E13=0,"-",F13/ABS(E13)) -> 0.13532018
A14: 800007 | B14: =VLOOKUP(A14,'Year-End TB'!$A:$F,2,0) -> NZ Franchise Sales | C14: International Franchise Revenue | D14: =VLOOKUP(A14,'Year-End TB'!$A:$F,5,0)*-1 -> 2071064 | E14: =VLOOKUP(A14,'Prior Year TB'!$A:$F,5,0)*-1 -> 1855000 | F14: =D14-E14 -> 216064 | G14: =IF(E14=0,"-",F14/ABS(E14)) -> 0.11647655
A15: 800008 | B15: =VLOOKUP(A15,'Year-End TB'!$A:$F,2,0) -> Investment income | C15: Investment Income | D15: =VLOOKUP(A15,'Year-End TB'!$A:$F,5,0)*-1 -> 3402096 | E15: =VLOOKUP(A15,'Prior Year TB'!$A:$F,5,0)*-1 -> 3105000 | F15: =D15-E15 -> 297096 | G15: =IF(E15=0,"-",F15/ABS(E15)) -> 0.095683092
A16: Total Revenue | D16: =SUM(D8:D15) -> 42166693 | E16: =SUM(E8:E15) -> 37800000 | F16: =D16-E16 -> 4366693 | G16: =IF(E16=0,"-",F16/ABS(E16)) -> 0.11552098

Sheet Year-End TB
A1: Evergreen Inc.
A2: Trial Balance Worksheet
A3: Year Ended December 31, 2024
A4: Chart of Account # | B4: Account Name | C4: Debit ($) | D4: Credit ($) | E4: Net ($) | F4: FS Caption
A5: 100001 | B5: TD Checking Account #9564 | C5: 2513545 | E5: 2513545 | F5: N/A
A6: 100002 | B6: TD Savings Account #8733 | C6: 1765738 | E6: 1765738 | F6: N/A
A7: 100003 | B7: Royal Bank of Canada Checking #286 | C7: 3962126 | E7: 3962126 | F7: N/A
A8: 100004 | B8: Petty Cash | C8: 1383 | E8: 1383 | F8: N/A
A9: 120000 | B9: Accounts receivable | C9: 4996958 | E9: 4996958 | F9: N/A
A10: 120001 | B10: Reserve for bad debts | D10: 5325000 | E10: -5325000 | F10: N/A
A11: 130001 | B11: Inventory | C11: 1335956 | E11: 1335956 | F11: N/A
A12: 140001 | B12: Prepaid insurance | C12: 22000 | E12: 22000 | F12: N/A
A13: 140002 | B13: Prepaid other expenses | C13: 91540 | E13: 91540 | F13: N/A
A14: 140003 | B14: Prepaid rent | C14: 15000 | E14: 15000 | F14: N/A
A15: 150003 | B15: Office supplies | C15: 5229 | E15: 5229 | F15: N/A
A16: 160001 | B16: Utility deposits | C16: 33000 | E16: 33000 | F16: N/A
A17: 170001 | B17: Notes receivable | C17: 4375000 | E17: 4375000 | F17: N/A
A18: 180001 | B18: Investments | C18: 14620000 | E18: 14620000 | F18: N/A
A19: 190001 | B19: Organization expense | C19: 2910819 | E19: 2910819 | F19: N/A
A20: 200000 | B20: Vehicles | C20: 2636860 | E20: 2636860 | F20: N/A
A21: 200001 | B21: Furniture and fixtures | C21: 2491451 | E21: 2491451 | F21: N/A
A22: 200002 | B22: Equipment | C22: 2749415 | E22: 2749415 | F22: N/A
... A24: 200004 | B24: Land | C24: 697470 | E24: 697470 | F24: N/A
A25: 210000 | B25: Accumulated depreciation - vehicles | D25: 3465559 | E25: -3465559 | F25: N/A
A26: 210001 | B26: Accumulated depreciation - F&F | D26: 5571502 | E26: -5571502 | F26: N/A
A27: 210002 | B27: Accumulated depreciation - equipment | D27: 3071883 | E27: -3071883 | F27: N/A
A28: 210003 | B28: Accumulated depreciation - buildings | D28: 1636960 | E28: -1636960 | F28: N/A
A29: 300000 | B29: Goodwill | C29: 1356642 | E29: 1356642 | F29: N/A
A30: 300001 | B30: Other intangible assets | C30: 4389321 | E30: 4389321 | F30: N/A
A31: 400000 | B31: Accounts payable | D31: 4708610 | E31: -4708610 | F31: N/A
A32: 400001 | B32: Sales tax payable | D32: 1327849 | E32: -1327849 | F32: N/A
A33: 400002 | B33: Federal withholding taxes payable | D33: 46144 | E33: -46144 | F33: N/A
A34: 400003 | B34: FICA taxes payable | D34: 61154 | E34: -61154 | F34: N/A
A35: 400004 | B35: State withholding taxes payable | D35: 26777 | E35: -26777 | F35: N/A
A36: 400005 | B36: Unemployment taxes payable | D36: 8895 | E36: -8895 | F36: N/A
A37: 500001 | B37: Accrued wages | D37: 49235 | E37: -49235 | F37: N/A
A38: 500002 | B38: Unearned revenue | D38: 468027 | E38: -468027 | F38: N/A
A39: 500003 | B39: Accrued income taxes | D39: 24272 | E39: -24272 | F39: N/A
A40: 600001 | B40: Credit card payable | D40: 68716 | E40: -68716 | F40: N/A
A41: 600002 | B41: Bank loan payable | D41: 2038196 | E41: -2038196 | F41: N/A
A42: 600003 | B42: Notes payable to third party | D42: 2912173 | E42: -2912173 | F42: N/A
A43: 700001 | B43: Owner's equity | D43: 2877999 | E43: -2877999 | F43: N/A
A44: 700002 | B44: Owner's drawing account | C44: 240904 | E44: 240904 | F44: N/A
A45: 700003 | B45: Common stock | D45: 1812976 | E45: -1812976 | F45: N/A
A46: 700004 | B46: Additional paid-in capital | D46: 6464202 | E46: -6464202 | F46: N/A
A47: 700005 | B47: Preferred stock | D47: 4164931 | E47: -4164931 | F47: N/A
A48: 700006 | B48: Retained earnings | D48: 4388842 | E48: -4388842 | F48: N/A
A49: 800001 | B49: Domestic Direct to Consumer Sales | D49: 23043496 | E49: -23043496 | F49: Domestic DTC Revenue
A50: 800002 | B50: AZ Franchise Sales | D50: 2229331 | E50: -2229331 | F50: Domestic Franchise Revenue
A51: 800003 | B51: CA Franchise Sales | D51: 5573328 | E51: -5573328 | F51: Domestic Franchise Revenue
A52: 800004 | B52: NYC Franchise Sales | D52: 2340798 | E52: -2340798 | F52: Domestic Franchise Revenue
A53: 800005 | B53: International Direct to Consumer Sales | D53: 1003199 | E53: -1003199 | F53: International DTC Revenue
A54: 800006 | B54: AUS Franchise Sales | D54: 2503381 | E54: -2503381 | F54: International Franchise Revenue
A55: 800007 | B55: NZ Franchise Sales | D55: 2071064 | E55: -2071064 | F55: International Franchise Revenue
A56: 800008 | B56: Investment income | D56: 3402096 | E56: -3402096 | F56: Investment Income
A57: 900001 | B57: Purchases | C57: 2395349 | E57: 2395349 | F57: N/A
A58: 900002 | B58: Freight | C58: 373652 | E58: 373652 | F58: N/A
A59: 900003 | B59: Cost of goods sold - materials | C59: 3027260 | E59: 3027260 | F59: N/A
A60: 900004 | B60: Cost of goods sold - direct expenses | C60: 7325600 | E60: 7325600 | F60: N/A
A61: 900005 | B61: Advertising | C61: 2737750 | E61: 2737750 | F61: N/A
A62: 900006 | B62: Bad debt expense | C62: 285000 | E62: 285000 | F62: N/A
A63: 900007 | B63: Charitable contributions | C63: 20000 | E63: 20000 | F63: N/A
A64: 900008 | B64: Contract labor | C64: 295766 | E64: 295766 | F64: N/A
A65: 900009 | B65: Delivery expense | C65: 757160 | E65: 757160 | F65: N/A
A66: 900010 | B66: Dues and subscriptions | C66: 20445 | E66: 20445 | F66: N/A
A67: 900011 | B67: Insurance | C67: 282065 | E67: 282065 | F67: N/A
A68: 900012 | B68: Maintenance | C68: 2585 | E68: 2585 | F68: N/A
... A75: 900019 | B75: Vehicle expenses | C75: 22134 | E75: 22134 | F75: N/A
A76: 910001 | B76: Purchase returns and allowances | D76: 285405 | E76: -285405 | F76: N/A
A77: 910002 | B77: Cost of goods sold - labor | C77: 5101792 | E77: 5101792 | F77: N/A
A78: 910003 | B78: Cost of goods sold - indirect exp. | C78: 1016680 | E78: 1016680 | F78: N/A
A79: 910004 | B79: Amortization | C79: 750000 | E79: 750000 | F79: N/A
A80: 910005 | B80: Bank charges | C80: 20000 | E80: 20000 | F80: N/A
A81: 910006 | B81: Commissions expense | C81: 1905750 | E81: 1905750 | F81: N/A
A82: 910007 | B82: Credit card fees expense | C82: 2378 | E82: 2378 | F82: N/A
A83: 910008 | B83: Depreciation | C83: 1132550 | E83: 1132550 | F83: N/A
A84: 910009 | B84: Client Entertainment | C84: 72017 | E84: 72017 | F84: N/A
A85: 910010 | B85: Interest expense | C85: 60146 | E85: 60146 | F85: N/A
A86: 910011 | B86: Miscellaneous | C86: 28480 | E86: 28480 | F86: N/A
A87: 910012 | B87: Operating supplies | C87: 23329 | E87: 23329 | F87: N/A
A88: 910013 | B88: Permits and licenses | C88: 42612 | E88: 42612 | F88: N/A
... A93: 910018 | B93: Wages | C93: 7748720 | E93: 7748720 | F93: N/A
A94: Totals | C94: =SUM(C5:C93) -> 92972000 | D94: =SUM(D5:D93) -> 92972000 | E94: =C94-D94 -> 0
A95: Difference | C95: =C94-D94 -> 0

Sheet Prior Year TB
A1: Evergreen Inc.
A2: Trial Balance Worksheet
A3: Year Ended December 31, 2023
A4: Chart of Account # | B4: Account Name | C4: Debit ($) | D4: Credit ($) | E4: Net ($) | F4: FS Caption
A5: 100001 | B5: TD Checking Account #9564 | C5: 2513545 | E5: 2513545 | F5: N/A
A6: 100002 | B6: TD Savings Account #8733 | C6: 1765738 | E6: 1765738 | F6: N/A
A7: 100003 | B7: Royal Bank of Canada Checking #286 | C7: 3962126 | E7: 3962126 | F7: N/A
A8: 100004 | B8: Petty Cash | C8: 1383 | E8: 1383 | F8: N/A
A9: 120000 | B9: Accounts receivable | C9: 4996958 | E9: 4996958 | F9: N/A
A10: 120001 | B10: Reserve for bad debts | D10: 5325000 | E10: -5325000 | F10: N/A
A11: 130001 | B11: Inventory | C11: 1335956 | E11: 1335956 | F11: N/A
A12: 140001 | B12: Prepaid insurance | C12: 22000 | E12: 22000 | F12: N/A
A13: 140002 | B13: Prepaid other expenses | C13: 91540 | E13: 91540 | F13: N/A
A14: 140003 | B14: Prepaid rent | C14: 15000 | E14: 15000 | F14: N/A
A15: 150003 | B15: Office supplies | C15: 5229 | E15: 5229 | F15: N/A
A16: 160001 | B16: Utility deposits | C16: 33000 | E16: 33000 | F16: N/A
A17: 170001 | B17: Notes receivable | C17: 4375000 | E17: 4375000 | F17: N/A
A18: 180001 | B18: Investments | C18: 14620000 | E18: 14620000 | F18: N/A
A19: 190001 | B19: Organization expense | C19: 2910819 | E19: 2910819 | F19: N/A
A20: 200000 | B20: Vehicles | C20: 2636860 | E20: 2636860 | F20: N/A
A21: 200001 | B21: Furniture and fixtures | C21: 2491451 | E21: 2491451 | F21: N/A
A22: 200002 | B22: Equipment | C22: 2749415 | E22: 2749415 | F22: N/A
... A24: 200004 | B24: Land | C24: 697470 | E24: 697470 | F24: N/A
A25: 210000 | B25: Accumulated depreciation - vehicles | D25: 3465559 | E25: -3465559 | F25: N/A
A26: 210001 | B26: Accumulated depreciation - F&F | D26: 5571502 | E26: -5571502 | F26: N/A
A27: 210002 | B27: Accumulated depreciation - equipment | D27: 3071883 | E27: -3071883 | F27: N/A
A28: 210003 | B28: Accumulated depreciation - buildings | D28: 1636960 | E28: -1636960 | F28: N/A
A29: 300000 | B29: Goodwill | C29: 1356642 | E29: 1356642 | F29: N/A
A30: 300001 | B30: Other intangible assets | C30: 4389321 | E30: 4389321 | F30: N/A
A31: 400000 | B31: Accounts payable | D31: 4708610 | E31: -4708610 | F31: N/A
A32: 400001 | B32: Sales tax payable | D32: 1327849 | E32: -1327849 | F32: N/A
A33: 400002 | B33: Federal withholding taxes payable | D33: 46144 | E33: -46144 | F33: N/A
A34: 400003 | B34: FICA taxes payable | D34: 61154 | E34: -61154 | F34: N/A
A35: 400004 | B35: State withholding taxes payable | D35: 26777 | E35: -26777 | F35: N/A
A36: 400005 | B36: Unemployment taxes payable | D36: 8895 | E36: -8895 | F36: N/A
A37: 500001 | B37: Accrued wages | D37: 49235 | E37: -49235 | F37: N/A
A38: 500002 | B38: Unearned revenue | D38: 468027 | E38: -468027 | F38: N/A
A39: 500003 | B39: Accrued income taxes | D39: 24272 | E39: -24272 | F39: N/A
A40: 600001 | B40: Credit card payable | D40: 68716 | E40: -68716 | F40: N/A
A41: 600002 | B41: Bank loan payable | D41: 2038196 | E41: -2038196 | F41: N/A
A42: 600003 | B42: Notes payable to third party | D42: 2912173 | E42: -2912173 | F42: N/A
A43: 700001 | B43: Owner's equity | D43: 2877999 | E43: -2877999 | F43: N/A
A44: 700002 | B44: Owner's drawing account | C44: 240904 | E44: 240904 | F44: N/A
A45: 700003 | B45: Common stock | D45: 1812976 | E45: -1812976 | F45: N/A
A46: 700004 | B46: Additional paid-in capital | D46: 6464202 | E46: -6464202 | F46: N/A
A47: 700005 | B47: Preferred stock | D47: 4164931 | E47: -4164931 | F47: N/A
A48: 700006 | B48: Retained earnings | D48: 4388842 | E48: -4388842 | F48: N/A
A49: 800001 | B49: Domestic Direct to Consumer Sales | D49: 20580000 | E49: -20580000 | F49: Domestic DTC Revenue
A50: 800002 | B50: AZ Franchise Sales | D50: 2050000 | E50: -2050000 | F50: Domestic Franchise Revenue
A51: 800003 | B51: CA Franchise Sales | D51: 5105000 | E51: -5105000 | F51: Domestic Franchise Revenue
A52: 800004 | B52: NYC Franchise Sales | D52: 2048000 | E52: -2048000 | F52: Domestic Franchise Revenue
A53: 800005 | B53: International Direct to Consumer Sales | D53: 852000 | E53: -852000 | F53: International DTC Revenue
A54: 800006 | B54: AUS Franchise Sales | D54: 2205000 | E54: -2205000 | F54: International Franchise Revenue
A55: 800007 | B55: NZ Franchise Sales | D55: 1855000 | E55: -1855000 | F55: International Franchise Revenue
A56: 800008 | B56: Investment income | D56: 3105000 | E56: -3105000 | F56: Investment Income
A57: 900001 | B57: Purchases | C57: 2395349 | E57: 2395349 | F57: N/A
A58: 900002 | B58: Freight | C58: 373652 | E58: 373652 | F58: N/A
A59: 900003 | B59: Cost of goods sold - materials | C59: 3027260 | E59: 3027260 | F59: N/A
A60: 900004 | B60: Cost of goods sold - direct expenses | C60: 7325600 | E60: 7325600 | F60: N/A
A61: 900005 | B61: Advertising | C61: 2737750 | E61: 2737750 | F61: N/A
A62: 900006 | B62: Bad debt expense | C62: 285000 | E62: 285000 | F62: N/A
A63: 900007 | B63: Charitable contributions | C63: 20000 | E63: 20000 | F63: N/A
A64: 900008 | B64: Contract labor | C64: 295766 | E64: 295766 | F64: N/A
A65: 900009 | B65: Delivery expense | C65: 757160 | E65: 757160 | F65: N/A
A66: 900010 | B66: Dues and subscriptions | C66: 20445 | E66: 20445 | F66: N/A
A67: 900011 | B67: Insurance | C67: 282065 | E67: 282065 | F67: N/A
A68: 900012 | B68: Maintenance | C68: 2585 | E68: 2585 | F68: N/A
... A75: 900019 | B75: Vehicle expenses | C75: 22134 | E75: 22134 | F75: N/A
A76: 910001 | B76: Purchase returns and allowances | D76: 285405 | E76: -285405 | F76: N/A
A77: 910002 | B77: Cost of goods sold - labor | C77: 5101792 | E77: 5101792 | F77: N/A
A78: 910003 | B78: Cost of goods sold - indirect exp. | C78: 1016680 | E78: 1016680 | F78: N/A
A79: 910004 | B79: Amortization | C79: 750000 | E79: 750000 | F79: N/A
A80: 910005 | B80: Bank charges | C80: 20000 | E80: 20000 | F80: N/A
A81: 910006 | B81: Commissions expense | C81: 1905750 | E81: 1905750 | F81: N/A
A82: 910007 | B82: Credit card fees expense | C82: 2378 | E82: 2378 | F82: N/A
A83: 910008 | B83: Depreciation | C83: 1132550 | E83: 1132550 | F83: N/A
A84: 910009 | B84: Client Entertainment | C84: 72017 | E84: 72017 | F84: N/A
A85: 910010 | B85: Interest expense | C85: 60146 | E85: 60146 | F85: N/A
A86: 910011 | B86: Miscellaneous | C86: 28480 | E86: 28480 | F86: N/A
A87: 910012 | B87: Operating supplies | C87: 23329 | E87: 23329 | F87: N/A
A88: 910013 | B88: Permits and licenses | C88: 42612 | E88: 42612 | F88: N/A
... A93: 910018 | B93: Wages | C93: 7748720 | E93: 7748720 | F93: N/A
A94: Totals | C94: =SUM(C5:C93) -> 92972000 | D94: =SUM(D5:D93) -> 88605307 | E94: =C94-D94 -> 4366693
A95: Difference | C95: =C94-D94 -> 4366693

Sheet Reconciliation
A1: Evergreen Inc.
A2: Revenue Reconciliation
A3: For the Year Ended December 31, 2024
A5: Purpose: This reconciliation uses SUMIF to tie revenue GL accounts to financial statement captions. Ties to the Year-End Trial Balance.
A7: Revenue Stream (FS Caption) | B7: Current Year 2024 ($) [SUMIF] | C7: Prior Year 2023 ($) [SUMIF] | D7: $ Change | E7: % Change | F7: Tie to Lead Sheet?
A8: Domestic DTC Revenue | B8: =SUMIF('Year-End TB'!$F:$F,A8,'Year-End TB'!$E:$E)*-1 -> 23043496 | C8: =SUMIF('Prior Year TB'!$F:$F,A8,'Prior Year TB'!$E:$E)*-1 -> 20580000 | D8: =B8-C8 -> 2463496 | E8: =IF(C8=0,"-",D8/ABS(C8)) -> 0.1197034 | F8: =IF(B8=('Revenue Lead Sheet'!D8),"✓ Agrees","✗ Variance") -> ✓ Agrees
A9: Domestic Franchise Revenue | B9: =SUMIF('Year-End TB'!$F:$F,A9,'Year-End TB'!$E:$E)*-1 -> 10143457 | C9: =SUMIF('Prior Year TB'!$F:$F,A9,'Prior Year TB'!$E:$E)*-1 -> 9203000 | D9: =B9-C9 -> 940457 | E9: =IF(C9=0,"-",D9/ABS(C9)) -> 0.10219026 | F9: =IF(B9=('Revenue Lead Sheet'!D9+'Revenue Lead Sheet'!D10+'Revenue Lead Sheet'!D11),"✓ Agrees","✗ Variance") -> ✓ Agrees
A10: International DTC Revenue | B10: =SUMIF('Year-End TB'!$F:$F,A10,'Year-End TB'!$E:$E)*-1 -> 1003199 | C10: =SUMIF('Prior Year TB'!$F:$F,A10,'Prior Year TB'!$E:$E)*-1 -> 852000 | D10: =B10-C10 -> 151199 | E10: =IF(C10=0,"-",D10/ABS(C10)) -> 0.17746362 | F10: =IF(B10=('Revenue Lead Sheet'!D12),"✓ Agrees","✗ Variance") -> ✓ Agrees
A11: International Franchise Revenue | B11: =SUMIF('Year-End TB'!$F:$F,A11,'Year-End TB'!$E:$E)*-1 -> 4574445 | C11: =SUMIF('Prior Year TB'!$F:$F,A11,'Prior Year TB'!$E:$E)*-1 -> 4060000 | D11: =B11-C11 -> 514445 | E11: =IF(C11=0,"-",D11/ABS(C11)) -> 0.12671059 | F11: =IF(B11=('Revenue Lead Sheet'!D13+'Revenue Lead Sheet'!D14),"✓ Agrees","✗ Variance") -> ✓ Agrees
A12: Investment Income | B12: =SUMIF('Year-End TB'!$F:$F,A12,'Year-End TB'!$E:$E)*-1 -> 3402096 | C12: =SUMIF('Prior Year TB'!$F:$F,A12,'Prior Year TB'!$E:$E)*-1 -> 3105000 | D12: =B12-C12 -> 297096 | E12: =IF(C12=0,"-",D12/ABS(C12)) -> 0.095683092 | F12: =IF(B12=('Revenue Lead Sheet'!D15),"✓ Agrees","✗ Variance") -> ✓ Agrees
A13: Total Revenue | B13: =SUM(B8:B12) -> 42166693 | C13: =SUM(C8:C12) -> 37800000 | D13: =B13-C13 -> 4366693 | E13: =IF(C13=0,"-",D13/ABS(C13)) -> 0.11552098 | F13: =IF(B13='Revenue Lead Sheet'!D16,"✓ Total Agrees","✗ Total Variance") -> ✓ Total Agrees
